Workbook

Sheet Read Me
A1: NVIDIA & Palantir — Investment Financial Model
A2: Base-case, five-year operating forecast and FCFF DCF. USD billions unless stated otherwise.
A4: Purpose | B4: Investment analysis framework for NVIDIA (NVDA) and Palantir Technologies (PLTR).
A5: Workbook contents | B5: Assumptions: editable blue-font drivers; company model tabs: actuals, forecasts, income statement and FCFF; DCF & Sensitivity: DCF output and WACC/terminal growth matrices; Sources: URLs and data notes.
A6: Color key | B6: Blue font = editable input / assumption. Black font = formula. Green fill = sourced actual or company guidance. Yellow fill = illustrative assumption / needs user review.
A7: Important limitation | B7: This is an educational model, not investment advice or a price target. Market prices and latest diluted share counts are not pulled live. DCF per-share outputs depend materially on editable net cash, diluted shares, WACC and terminal growth.
A8: NVIDIA reporting period | B8: NVIDIA fiscal years differ from calendar years. The forecast starts FY2027E; latest actual anchor in this workbook is Q2 FY2027 and first-half FY2027.
A9: Palantir reporting period | B9: Calendar years. Q1 and Q2 2026 actuals are sourced; full-year 2026 revenue and adjusted FCF use company guidance / run-rate context, while GAAP forecast line items are modeled.
A10: Forecast logic | B10: Revenue = prior year revenue × (1 + growth). Gross profit = revenue × gross margin. Operating income = revenue × operating margin. FCFF = NOPAT + D&A − CapEx − change in NWC.
A11: DCF logic | B11: Enterprise value = PV of explicit FCFF + PV of terminal value. Equity value = enterprise value + net cash (editable approximation). Per-share value = equity value / diluted shares.
A12: Use carefully | B12: Do not compare Palantir adjusted free cash flow with GAAP FCFF without reconciling stock-based compensation and other adjustments. Model DCF uses normalized unlevered cash flow assumptions.

Sheet Assumptions
A1: Editable Assumptions
A2: Blue font cells are user-editable. Assumptions are illustrative unless explicitly labelled sourced.
A4: Driver | B4: NVIDIA | C4: Palantir | D4: Basis / note
A5: FY2027 / 2026 revenue base (USD bn) | B5: 350 | C5: 7.65 | D5: NVDA FY2027 base is illustrative; PLTR FY2026 revenue guidance midpoint from Q1 2026 release ($7.650–$7.662bn).
A6: FY2028 / 2027 revenue growth | B6: 0.2 | C6: 0.5 | D6: Illustrative base-case forecast.
A7: FY2029 / 2028 revenue growth | B7: 0.15 | C7: 0.35 | D7: Illustrative base-case forecast.
A8: FY2030 / 2029 revenue growth | B8: 0.15 | C8: 0.28 | D8: Illustrative base-case forecast.
A9: FY2031 / 2030 revenue growth | B9: 0.1 | C9: 0.22 | D9: Illustrative base-case forecast.
A10: Gross margin - starting | B10: 0.75 | C10: 0.8 | D10: NVDA Q2 FY2027 reported GAAP gross margin 75%; PLTR 80% is a modeling assumption.
A11: Gross margin annual change | B11: -0.01 | C11: 0 | D11: Illustrative annual change in percentage points.
A12: Operating margin - starting | B12: 0.6 | C12: 0.35 | D12: Illustrative normalized margin assumptions; NVDA Q2 GAAP operating margin was about 66.2%, PLTR Q2 GAAP op margin ~47% (actual quarter, not normalized).
A13: Operating margin annual change | B13: -0.02 | C13: 0.02 | D13: Illustrative annual change in percentage points.
A14: Tax rate | B14: 0.17 | C14: 0.2 | D14: NVDA FY2027 company tax outlook 16–18%; PLTR normalized assumption.
A15: D&A as % revenue | B15: 0.025 | C15: 0.015 | D15: Illustrative assumption.
A16: CapEx as % revenue | B16: 0.035 | C16: 0.01 | D16: Illustrative assumption.
... A22: Current share price ($) | B22: 180 | C22: 150 | D22: Placeholder only — not a live quote. Replace with current market price before using implied upside.

Sheet NVIDIA Model
A1: NVIDIA — Operating Model
A2: USD billions, except growth/margins. Green = reported actual / guidance; yellow = forecast assumptions or modeled estimates.
A4: Metric | B4: FY2027E | C4: FY2028E | D4: FY2029E | E4: FY2030E | F4: FY2031E
A5: Revenue | B5: =Assumptions!B5 | C5: =B5*(1+Assumptions!B6) | D5: =C5*(1+Assumptions!B7) | E5: =D5*(1+Assumptions!B8) | F5: =E5*(1+Assumptions!B9)
A6: Revenue growth | B6: =NA() | C6: =Assumptions!B6 | D6: =Assumptions!B7 | E6: =Assumptions!B8 | F6: =Assumptions!B9
A7: Gross margin | B7: =Assumptions!B10+0*Assumptions!B11 | C7: =Assumptions!B10+1*Assumptions!B11 | D7: =Assumptions!B10+2*Assumptions!B11 | E7: =Assumptions!B10+3*Assumptions!B11 | F7: =Assumptions!B10+4*Assumptions!B11
A8: Gross profit | B8: =B5*B7 | C8: =C5*C7 | D8: =D5*D7 | E8: =E5*E7 | F8: =F5*F7
A9: Operating margin | B9: =Assumptions!B12+0*Assumptions!B13 | C9: =Assumptions!B12+1*Assumptions!B13 | D9: =Assumptions!B12+2*Assumptions!B13 | E9: =Assumptions!B12+3*Assumptions!B13 | F9: =Assumptions!B12+4*Assumptions!B13
A10: Operating income (EBIT) | B10: =B5*B9 | C10: =C5*C9 | D10: =D5*D9 | E10: =E5*E9 | F10: =F5*F9
A11: Tax rate | B11: =Assumptions!B14 | C11: =Assumptions!B14 | D11: =Assumptions!B14 | E11: =Assumptions!B14 | F11: =Assumptions!B14
A12: NOPAT | B12: =B10*(1-B11) | C12: =C10*(1-C11) | D12: =D10*(1-D11) | E12: =E10*(1-E11) | F12: =F10*(1-F11)
A13: D&A | B13: =B5*Assumptions!B15 | C13: =C5*Assumptions!B15 | D13: =D5*Assumptions!B15 | E13: =E5*Assumptions!B15 | F13: =F5*Assumptions!B15
A14: CapEx | B14: =B5*Assumptions!B16 | C14: =C5*Assumptions!B16 | D14: =D5*Assumptions!B16 | E14: =E5*Assumptions!B16 | F14: =F5*Assumptions!B16
A15: Change in NWC | B15: 0 | C15: =(C5-B5)*Assumptions!B17 | D15: =(D5-C5)*Assumptions!B17 | E15: =(E5-D5)*Assumptions!B17 | F15: =(F5-E5)*Assumptions!B17
A16: Unlevered free cash flow | B16: =B12+B13-B14-B15 | C16: =C12+C13-C14-C15 | D16: =D12+D13-D14-D15 | E16: =E12+E13-E14-E15 | F16: =F12+F13-F14-F15
A17: FCFF margin | B17: =B16/B5 | C17: =C16/C5 | D17: =D16/D5 | E17: =E16/E5 | F17: =F16/F5
A20: Reported data anchors (not forecast)
A21: Q2 FY2027 revenue | B21: 96.221 | C21: Reported quarter ended Jul 26, 2026; source link in Sources.
A22: Q2 FY2027 GAAP gross margin | B22: 0.75 | C22: Reported.
A23: Q2 FY2027 GAAP operating income | B23: 63.734 | C23: Reported.
A24: Q2 FY2027 GAAP net income | B24: 59.688 | C24: Reported.
A25: H1 FY2027 revenue | B25: 177.837 | C25: Reported six months ended Jul 26, 2026.
A26: H1 FY2027 GAAP operating income | B26: 117.27 | C26: Reported six months ended Jul 26, 2026.
A27: H1 FY2027 free cash flow | B27: 69.895 | C27: Reported company free cash flow for first six months; non-GAAP-defined company measure.

Sheet Palantir Model
A1: Palantir — Operating Model
A2: USD billions, except growth/margins. Green = reported actual / guidance; yellow = forecast assumptions or modeled estimates.
A4: Metric | B4: 2026E | C4: 2027E | D4: 2028E | E4: 2029E | F4: 2030E
A5: Revenue | B5: =Assumptions!C5 | C5: =B5*(1+Assumptions!C6) | D5: =C5*(1+Assumptions!C7) | E5: =D5*(1+Assumptions!C8) | F5: =E5*(1+Assumptions!C9)
A6: Revenue growth | B6: =NA() | C6: =Assumptions!C6 | D6: =Assumptions!C7 | E6: =Assumptions!C8 | F6: =Assumptions!C9
A7: Gross margin | B7: =Assumptions!C10+0*Assumptions!C11 | C7: =Assumptions!C10+1*Assumptions!C11 | D7: =Assumptions!C10+2*Assumptions!C11 | E7: =Assumptions!C10+3*Assumptions!C11 | F7: =Assumptions!C10+4*Assumptions!C11
A8: Gross profit | B8: =B5*B7 | C8: =C5*C7 | D8: =D5*D7 | E8: =E5*E7 | F8: =F5*F7
A9: Operating margin | B9: =Assumptions!C12+0*Assumptions!C13 | C9: =Assumptions!C12+1*Assumptions!C13 | D9: =Assumptions!C12+2*Assumptions!C13 | E9: =Assumptions!C12+3*Assumptions!C13 | F9: =Assumptions!C12+4*Assumptions!C13
A10: Operating income (EBIT) | B10: =B5*B9 | C10: =C5*C9 | D10: =D5*D9 | E10: =E5*E9 | F10: =F5*F9
A11: Tax rate | B11: =Assumptions!C14 | C11: =Assumptions!C14 | D11: =Assumptions!C14 | E11: =Assumptions!C14 | F11: =Assumptions!C14
A12: NOPAT | B12: =B10*(1-B11) | C12: =C10*(1-C11) | D12: =D10*(1-D11) | E12: =E10*(1-E11) | F12: =F10*(1-F11)
A13: D&A | B13: =B5*Assumptions!C15 | C13: =C5*Assumptions!C15 | D13: =D5*Assumptions!C15 | E13: =E5*Assumptions!C15 | F13: =F5*Assumptions!C15
A14: CapEx | B14: =B5*Assumptions!C16 | C14: =C5*Assumptions!C16 | D14: =D5*Assumptions!C16 | E14: =E5*Assumptions!C16 | F14: =F5*Assumptions!C16
A15: Change in NWC | B15: 0 | C15: =(C5-B5)*Assumptions!C17 | D15: =(D5-C5)*Assumptions!C17 | E15: =(E5-D5)*Assumptions!C17 | F15: =(F5-E5)*Assumptions!C17
A16: Unlevered free cash flow | B16: =B12+B13-B14-B15 | C16: =C12+C13-C14-C15 | D16: =D12+D13-D14-D15 | E16: =E12+E13-E14-E15 | F16: =F12+F13-F14-F15
A17: FCFF margin | B17: =B16/B5 | C17: =C16/C5 | D17: =D16/D5 | E17: =E16/E5 | F17: =F16/F5
A20: Reported data anchors (not forecast)
A21: Q2 2026 revenue | B21: 1.94 | C21: Reported; Q2 Business Update.
A22: Q2 2026 adjusted free cash flow | B22: 1.22 | C22: Reported non-GAAP adjusted FCF; do not equate with GAAP FCFF.
A23: Q2 2026 adjusted operating income | B23: 1.19 | C23: Reported non-GAAP adjusted operating income.
A24: Q1 2026 revenue | B24: 1.633 | C24: Reported quarter ended Mar 31, 2026.
A25: Q1 2026 GAAP operating income | B25: 0.754 | C25: Reported quarter ended Mar 31, 2026.
A26: Q1 2026 cash + marketable securities | B26: 8.026 | C26: Reported balance sheet at Mar 31, 2026.

Sheet DCF & Sensitivity
A1: DCF Valuation & Sensitivity
A2: Base-case FCFF DCF; outputs are model-driven and depend on editable assumptions.
A4: Valuation metric | B4: NVIDIA | C4: Palantir
A5: WACC | B5: =Assumptions!B18 | C5: =Assumptions!C18
A6: Terminal growth | B6: =Assumptions!B19 | C6: =Assumptions!C19
A7: PV of forecast FCFF | B7: =SUMPRODUCT('NVIDIA Model'!B16:F16,1/(1+B5)^{1,2,3,4,5}) | C7: =SUMPRODUCT('Palantir Model'!B16:F16,1/(1+C5)^{1,2,3,4,5})
A8: Terminal value | B8: ='NVIDIA Model'!F16*(1+B6)/(B5-B6) | C8: ='Palantir Model'!F16*(1+C6)/(C5-C6)
A9: PV of terminal value | B9: =B8/(1+B5)^5 | C9: =C8/(1+C5)^5
A10: Enterprise value | B10: =B7+B9 | C10: =C7+C9
A11: Net cash / (debt) | B11: =Assumptions!B20 | C11: =Assumptions!C20
A12: Equity value | B12: =B10+B11 | C12: =C10+C11
A13: Diluted shares (bn) | B13: =Assumptions!B21 | C13: =Assumptions!C21
A14: Implied value per share | B14: =B12/B13 | C14: =C12/C13
A15: Placeholder current share price | B15: =Assumptions!B22 | C15: =Assumptions!C22
A16: Implied upside / (downside) | B16: =B14/B15-1 | C16: =C14/C15-1
A19: Sensitivity: implied value per share — NVIDIA
A20: WACC \ g | B20: 0.02 | C20: 0.025 | D20: 0.03 | E20: 0.035 | F20: 0.04
A21: 0.075 | B21: =(SUMPRODUCT('NVIDIA Model'!$B$16:$F$16,1/(1+$A21)^{1,2,3,4,5})+('NVIDIA Model'!$F$16*(1+B$20)/($A21-B$20))/(1+$A21)^5+Assumptions!$B$20)/Assumptions!$B$21 | C21: =(SUMPRODUCT('NVIDIA Model'!$B$16:$F$16,1/(1+$A21)^{1,2,3,4,5})+('NVIDIA Model'!$F$16*(1+C$20)/($A21-C$20))/(1+$A21)^5+Assumptions!$B$20)/Assumptions!$B$21 | D21: =(SUMPRODUCT('NVIDIA Model'!$B$16:$F$16,1/(1+$A21)^{1,2,3,4,5})+('NVIDIA Model'!$F$16*(1+D$20)/($A21-D$20))/(1+$A21)^5+Assumptions!$B$20)/Assumptions!$B$21 | E21: =(SUMPRODUCT('NVIDIA Model'!$B$16:$F$16,1/(1+$A21)^{1,2,3,4,5})+('NVIDIA Model'!$F$16*(1+E$20)/($A21-E$20))/(1+$A21)^5+Assumptions!$B$20)/Assumptions!$B$21 | F21: =(SUMPRODUCT('NVIDIA Model'!$B$16:$F$16,1/(1+$A21)^{1,2,3,4,5})+('NVIDIA Model'!$F$16*(1+F$20)/($A21-F$20))/(1+$A21)^5+Assumptions!$B$20)/Assumptions!$B$21
A22: 0.08 | B22: =(SUMPRODUCT('NVIDIA Model'!$B$16:$F$16,1/(1+$A22)^{1,2,3,4,5})+('NVIDIA Model'!$F$16*(1+B$20)/($A22-B$20))/(1+$A22)^5+Assumptions!$B$20)/Assumptions!$B$21 | C22: =(SUMPRODUCT('NVIDIA Model'!$B$16:$F$16,1/(1+$A22)^{1,2,3,4,5})+('NVIDIA Model'!$F$16*(1+C$20)/($A22-C$20))/(1+$A22)^5+Assumptions!$B$20)/Assumptions!$B$21 | D22: =(SUMPRODUCT('NVIDIA Model'!$B$16:$F$16,1/(1+$A22)^{1,2,3,4,5})+('NVIDIA Model'!$F$16*(1+D$20)/($A22-D$20))/(1+$A22)^5+Assumptions!$B$20)/Assumptions!$B$21 | E22: =(SUMPRODUCT('NVIDIA Model'!$B$16:$F$16,1/(1+$A22)^{1,2,3,4,5})+('NVIDIA Model'!$F$16*(1+E$20)/($A22-E$20))/(1+$A22)^5+Assumptions!$B$20)/Assumptions!$B$21 | F22: =(SUMPRODUCT('NVIDIA Model'!$B$16:$F$16,1/(1+$A22)^{1,2,3,4,5})+('NVIDIA Model'!$F$16*(1+F$20)/($A22-F$20))/(1+$A22)^5+Assumptions!$B$20)/Assumptions!$B$21
A23: 0.085 | B23: =(SUMPRODUCT('NVIDIA Model'!$B$16:$F$16,1/(1+$A23)^{1,2,3,4,5})+('NVIDIA Model'!$F$16*(1+B$20)/($A23-B$20))/(1+$A23)^5+Assumptions!$B$20)/Assumptions!$B$21 | C23: =(SUMPRODUCT('NVIDIA Model'!$B$16:$F$16,1/(1+$A23)^{1,2,3,4,5})+('NVIDIA Model'!$F$16*(1+C$20)/($A23-C$20))/(1+$A23)^5+Assumptions!$B$20)/Assumptions!$B$21 | D23: =(SUMPRODUCT('NVIDIA Model'!$B$16:$F$16,1/(1+$A23)^{1,2,3,4,5})+('NVIDIA Model'!$F$16*(1+D$20)/($A23-D$20))/(1+$A23)^5+Assumptions!$B$20)/Assumptions!$B$21 | E23: =(SUMPRODUCT('NVIDIA Model'!$B$16:$F$16,1/(1+$A23)^{1,2,3,4,5})+('NVIDIA Model'!$F$16*(1+E$20)/($A23-E$20))/(1+$A23)^5+Assumptions!$B$20)/Assumptions!$B$21 | F23: =(SUMPRODUCT('NVIDIA Model'!$B$16:$F$16,1/(1+$A23)^{1,2,3,4,5})+('NVIDIA Model'!$F$16*(1+F$20)/($A23-F$20))/(1+$A23)^5+Assumptions!$B$20)/Assumptions!$B$21
A24: 0.09 | B24: =(SUMPRODUCT('NVIDIA Model'!$B$16:$F$16,1/(1+$A24)^{1,2,3,4,5})+('NVIDIA Model'!$F$16*(1+B$20)/($A24-B$20))/(1+$A24)^5+Assumptions!$B$20)/Assumptions!$B$21 | C24: =(SUMPRODUCT('NVIDIA Model'!$B$16:$F$16,1/(1+$A24)^{1,2,3,4,5})+('NVIDIA Model'!$F$16*(1+C$20)/($A24-C$20))/(1+$A24)^5+Assumptions!$B$20)/Assumptions!$B$21 | D24: =(SUMPRODUCT('NVIDIA Model'!$B$16:$F$16,1/(1+$A24)^{1,2,3,4,5})+('NVIDIA Model'!$F$16*(1+D$20)/($A24-D$20))/(1+$A24)^5+Assumptions!$B$20)/Assumptions!$B$21 | E24: =(SUMPRODUCT('NVIDIA Model'!$B$16:$F$16,1/(1+$A24)^{1,2,3,4,5})+('NVIDIA Model'!$F$16*(1+E$20)/($A24-E$20))/(1+$A24)^5+Assumptions!$B$20)/Assumptions!$B$21 | F24: =(SUMPRODUCT('NVIDIA Model'!$B$16:$F$16,1/(1+$A24)^{1,2,3,4,5})+('NVIDIA Model'!$F$16*(1+F$20)/($A24-F$20))/(1+$A24)^5+Assumptions!$B$20)/Assumptions!$B$21
A25: 0.095 | B25: =(SUMPRODUCT('NVIDIA Model'!$B$16:$F$16,1/(1+$A25)^{1,2,3,4,5})+('NVIDIA Model'!$F$16*(1+B$20)/($A25-B$20))/(1+$A25)^5+Assumptions!$B$20)/Assumptions!$B$21 | C25: =(SUMPRODUCT('NVIDIA Model'!$B$16:$F$16,1/(1+$A25)^{1,2,3,4,5})+('NVIDIA Model'!$F$16*(1+C$20)/($A25-C$20))/(1+$A25)^5+Assumptions!$B$20)/Assumptions!$B$21 | D25: =(SUMPRODUCT('NVIDIA Model'!$B$16:$F$16,1/(1+$A25)^{1,2,3,4,5})+('NVIDIA Model'!$F$16*(1+D$20)/($A25-D$20))/(1+$A25)^5+Assumptions!$B$20)/Assumptions!$B$21 | E25: =(SUMPRODUCT('NVIDIA Model'!$B$16:$F$16,1/(1+$A25)^{1,2,3,4,5})+('NVIDIA Model'!$F$16*(1+E$20)/($A25-E$20))/(1+$A25)^5+Assumptions!$B$20)/Assumptions!$B$21 | F25: =(SUMPRODUCT('NVIDIA Model'!$B$16:$F$16,1/(1+$A25)^{1,2,3,4,5})+('NVIDIA Model'!$F$16*(1+F$20)/($A25-F$20))/(1+$A25)^5+Assumptions!$B$20)/Assumptions!$B$21
A28: Sensitivity: implied value per share — Palantir
A29: WACC \ g | B29: 0.025 | C29: 0.03 | D29: 0.035 | E29: 0.04 | F29: 0.045
A30: 0.08 | B30: =(SUMPRODUCT('Palantir Model'!$B$16:$F$16,1/(1+$A30)^{1,2,3,4,5})+('Palantir Model'!$F$16*(1+B$29)/($A30-B$29))/(1+$A30)^5+Assumptions!$C$20)/Assumptions!$C$21 | C30: =(SUMPRODUCT('Palantir Model'!$B$16:$F$16,1/(1+$A30)^{1,2,3,4,5})+('Palantir Model'!$F$16*(1+C$29)/($A30-C$29))/(1+$A30)^5+Assumptions!$C$20)/Assumptions!$C$21 | D30: =(SUMPRODUCT('Palantir Model'!$B$16:$F$16,1/(1+$A30)^{1,2,3,4,5})+('Palantir Model'!$F$16*(1+D$29)/($A30-D$29))/(1+$A30)^5+Assumptions!$C$20)/Assumptions!$C$21 | E30: =(SUMPRODUCT('Palantir Model'!$B$16:$F$16,1/(1+$A30)^{1,2,3,4,5})+('Palantir Model'!$F$16*(1+E$29)/($A30-E$29))/(1+$A30)^5+Assumptions!$C$20)/Assumptions!$C$21 | F30: =(SUMPRODUCT('Palantir Model'!$B$16:$F$16,1/(1+$A30)^{1,2,3,4,5})+('Palantir Model'!$F$16*(1+F$29)/($A30-F$29))/(1+$A30)^5+Assumptions!$C$20)/Assumptions!$C$21
A31: 0.085 | B31: =(SUMPRODUCT('Palantir Model'!$B$16:$F$16,1/(1+$A31)^{1,2,3,4,5})+('Palantir Model'!$F$16*(1+B$29)/($A31-B$29))/(1+$A31)^5+Assumptions!$C$20)/Assumptions!$C$21 | C31: =(SUMPRODUCT('Palantir Model'!$B$16:$F$16,1/(1+$A31)^{1,2,3,4,5})+('Palantir Model'!$F$16*(1+C$29)/($A31-C$29))/(1+$A31)^5+Assumptions!$C$20)/Assumptions!$C$21 | D31: =(SUMPRODUCT('Palantir Model'!$B$16:$F$16,1/(1+$A31)^{1,2,3,4,5})+('Palantir Model'!$F$16*(1+D$29)/($A31-D$29))/(1+$A31)^5+Assumptions!$C$20)/Assumptions!$C$21 | E31: =(SUMPRODUCT('Palantir Model'!$B$16:$F$16,1/(1+$A31)^{1,2,3,4,5})+('Palantir Model'!$F$16*(1+E$29)/($A31-E$29))/(1+$A31)^5+Assumptions!$C$20)/Assumptions!$C$21 | F31: =(SUMPRODUCT('Palantir Model'!$B$16:$F$16,1/(1+$A31)^{1,2,3,4,5})+('Palantir Model'!$F$16*(1+F$29)/($A31-F$29))/(1+$A31)^5+Assumptions!$C$20)/Assumptions!$C$21
A32: 0.09 | B32: =(SUMPRODUCT('Palantir Model'!$B$16:$F$16,1/(1+$A32)^{1,2,3,4,5})+('Palantir Model'!$F$16*(1+B$29)/($A32-B$29))/(1+$A32)^5+Assumptions!$C$20)/Assumptions!$C$21 | C32: =(SUMPRODUCT('Palantir Model'!$B$16:$F$16,1/(1+$A32)^{1,2,3,4,5})+('Palantir Model'!$F$16*(1+C$29)/($A32-C$29))/(1+$A32)^5+Assumptions!$C$20)/Assumptions!$C$21 | D32: =(SUMPRODUCT('Palantir Model'!$B$16:$F$16,1/(1+$A32)^{1,2,3,4,5})+('Palantir Model'!$F$16*(1+D$29)/($A32-D$29))/(1+$A32)^5+Assumptions!$C$20)/Assumptions!$C$21 | E32: =(SUMPRODUCT('Palantir Model'!$B$16:$F$16,1/(1+$A32)^{1,2,3,4,5})+('Palantir Model'!$F$16*(1+E$29)/($A32-E$29))/(1+$A32)^5+Assumptions!$C$20)/Assumptions!$C$21 | F32: =(SUMPRODUCT('Palantir Model'!$B$16:$F$16,1/(1+$A32)^{1,2,3,4,5})+('Palantir Model'!$F$16*(1+F$29)/($A32-F$29))/(1+$A32)^5+Assumptions!$C$20)/Assumptions!$C$21
A33: 0.095 | B33: =(SUMPRODUCT('Palantir Model'!$B$16:$F$16,1/(1+$A33)^{1,2,3,4,5})+('Palantir Model'!$F$16*(1+B$29)/($A33-B$29))/(1+$A33)^5+Assumptions!$C$20)/Assumptions!$C$21 | C33: =(SUMPRODUCT('Palantir Model'!$B$16:$F$16,1/(1+$A33)^{1,2,3,4,5})+('Palantir Model'!$F$16*(1+C$29)/($A33-C$29))/(1+$A33)^5+Assumptions!$C$20)/Assumptions!$C$21 | D33: =(SUMPRODUCT('Palantir Model'!$B$16:$F$16,1/(1+$A33)^{1,2,3,4,5})+('Palantir Model'!$F$16*(1+D$29)/($A33-D$29))/(1+$A33)^5+Assumptions!$C$20)/Assumptions!$C$21 | E33: =(SUMPRODUCT('Palantir Model'!$B$16:$F$16,1/(1+$A33)^{1,2,3,4,5})+('Palantir Model'!$F$16*(1+E$29)/($A33-E$29))/(1+$A33)^5+Assumptions!$C$20)/Assumptions!$C$21 | F33: =(SUMPRODUCT('Palantir Model'!$B$16:$F$16,1/(1+$A33)^{1,2,3,4,5})+('Palantir Model'!$F$16*(1+F$29)/($A33-F$29))/(1+$A33)^5+Assumptions!$C$20)/Assumptions!$C$21
A34: 0.1 | B34: =(SUMPRODUCT('Palantir Model'!$B$16:$F$16,1/(1+$A34)^{1,2,3,4,5})+('Palantir Model'!$F$16*(1+B$29)/($A34-B$29))/(1+$A34)^5+Assumptions!$C$20)/Assumptions!$C$21 | C34: =(SUMPRODUCT('Palantir Model'!$B$16:$F$16,1/(1+$A34)^{1,2,3,4,5})+('Palantir Model'!$F$16*(1+C$29)/($A34-C$29))/(1+$A34)^5+Assumptions!$C$20)/Assumptions!$C$21 | D34: =(SUMPRODUCT('Palantir Model'!$B$16:$F$16,1/(1+$A34)^{1,2,3,4,5})+('Palantir Model'!$F$16*(1+D$29)/($A34-D$29))/(1+$A34)^5+Assumptions!$C$20)/Assumptions!$C$21 | E34: =(SUMPRODUCT('Palantir Model'!$B$16:$F$16,1/(1+$A34)^{1,2,3,4,5})+('Palantir Model'!$F$16*(1+E$29)/($A34-E$29))/(1+$A34)^5+Assumptions!$C$20)/Assumptions!$C$21 | F34: =(SUMPRODUCT('Palantir Model'!$B$16:$F$16,1/(1+$A34)^{1,2,3,4,5})+('Palantir Model'!$F$16*(1+F$29)/($A34-F$29))/(1+$A34)^5+Assumptions!$C$20)/Assumptions!$C$21
A37: Sensitivity grids assume all other inputs remain constant. Avoid terminal growth >= WACC.

Sheet Sources
A1: Sources & Actual Data Notes
A2: Primary company sources reviewed October 12, 2026. Forecast inputs remain assumptions unless noted.
A4: Company / data | B4: Source | C4: Model use / note
A5: NVIDIA Q2 FY2027 results | B5: https://investor.nvidia.com/news/press-release-details/2026/NVIDIA-Announces-Financial-Results-for-Second-Quarter-Fiscal-2027/ | C5: Q2 revenue $96.221bn, GAAP gross margin 75.0%, operating income $63.734bn, net income $59.688bn; H1 revenue $177.837bn; H1 company-defined FCF $69.895bn.
A6: NVIDIA Q2 FY2027 detailed release | B6: https://investor.nvidia.com/news/press-release-details/2026/NVIDIA-Announces-Financial-Results-for-Second-Quarter-Fiscal-2027/default.aspx | C6: Q3 FY2027 revenue guidance $108bn ±2%; FY2027 tax-rate outlook 16–18%; diluted weighted average shares Q2 24.285bn.
A7: Palantir Q2 2026 Business Update (PDF) | B7: https://investors.palantir.com/files/Palantir%20-%20Q2%202026%20Business%20Update.pdf | C7: Q2 revenue $1.94bn; adjusted FCF $1.22bn; adjusted operating income $1.19bn; US commercial revenue $764m.
A8: Palantir Q2 2026 Shareholder Letter | B8: https://www.palantir.com/q2-2026-letter/en/ | C8: Q2 2026 reported revenue growth of 93% year over year; revenue $1.9bn (rounded).
A9: Palantir Q1 2026 earnings release | B9: https://investors.palantir.com/news-details/2026/Palantir-Reports-Q1-2026-U-S--Revenue-Growth-of-104-YY-and-Revenue-Growth-of-85/ | C9: Q1 revenue $1.633bn; GAAP operating income $0.754bn; cash + marketable securities ~$8.026bn; FY2026 revenue guidance $7.650–$7.662bn.
A10: Palantir Quarterly Results | B10: https://investors.palantir.com/financials/quarterly-results | C10: Investor relations index for quarterly reports and filings.
